LICENSE.txt
MANIFEST.in
README.md
setup.py
cloudchain/__init__.py
cloudchain/cloudchain.py
cloudchain/command_line.py
cloudchain.egg-info/PKG-INFO
cloudchain.egg-info/SOURCES.txt
cloudchain.egg-info/dependency_links.txt
cloudchain.egg-info/entry_points.txt
cloudchain.egg-info/requires.txt
cloudchain.egg-info/top_level.txt