Metadata-Version: 1.1
Name: cloudchain
Version: 0.1.4
Summary: Secure, easy secrets.
Home-page: https://github.com/targetsmart-devops/cloudchain.git
Author: Jonathan Buys
Author-email: jonathan.buys@targetsmart.com
License: UNKNOWN
Download-URL: https://github.com/targetsmart-devops/cloudchain.git
Keywords: secrets,password,account
Platform: UNKNOWN
